README.txt
setup.cfg
setup.py
collective/__init__.py
collective.ajaxkeywords.egg-info/PKG-INFO
collective.ajaxkeywords.egg-info/SOURCES.txt
collective.ajaxkeywords.egg-info/dependency_links.txt
collective.ajaxkeywords.egg-info/entry_points.txt
collective.ajaxkeywords.egg-info/namespace_packages.txt
collective.ajaxkeywords.egg-info/not-zip-safe
collective.ajaxkeywords.egg-info/paster_plugins.txt
collective.ajaxkeywords.egg-info/requires.txt
collective.ajaxkeywords.egg-info/top_level.txt
collective/ajaxkeywords/__init__.py
collective/ajaxkeywords/browser.py
collective/ajaxkeywords/tests.py