Metadata-Version: 1.0
Name: collective.ajaxkeywords
Version: 0.1
Summary: A replacement for the Plone keywords viewlet based on a jquery tag handler.
Home-page: https://bitbucket.org/domruf/collective.ajaxkeywords
Author: Dominik Ruf
Author-email: dominikruf@gmail.com
License: GPL
Platform: UNKNOWN
Classifier: Framework :: Plone
Classifier: Programming Language :: Python
